{
  "rep": "AP",
  "rep_name": "Amit Patel",
  "generated_at": "2026-06-16",
  "store": {
    "dlref": "KA090",
    "curef": "KA090",
    "customer_name": "A A Owaish Maize Depot Pty Ltd",
    "town": "Next to U Save Randzus Complex",
    "accno": "KA090",
    "last_purchase_date": "10 Jun 2026",
    "last_purchase_amt": 1050.0,
    "last_purchase_prod": "200mm x 10m Membrane",
    "total_12m": 70739.23999999999,
    "velocity_category": "growing",
    "health_tier": "At-Risk",
    "health_score": 46.6,
    "is_recovery": false,
    "d_current": 11923.28,
    "d30": 0.0,
    "d60": 10717.62,
    "d90": 0.0,
    "d_total": 22640.9,
    "shared_account": false
  },
  "invoice": {
    "invoice_no": "131627",
    "date": "10 Jun 2026",
    "lines": [
      {
        "prodname": "1L HIGH GLOSS (MQ) BURGANDY",
        "qty": 3.0,
        "unit_price": 82.5,
        "value": 247.5
      },
      {
        "prodname": "20L UNIVERSAL ROOF BURGANDY",
        "qty": 2.0,
        "unit_price": 580.0,
        "value": 1160.0
      },
      {
        "prodname": "20L UNIVERSAL ROOF RED",
        "qty": 3.0,
        "unit_price": 580.0,
        "value": 1740.0
      },
      {
        "prodname": "5L RAINPROOF BLACK",
        "qty": 12.0,
        "unit_price": 109.25,
        "value": 1311.0
      },
      {
        "prodname": "5L RAINPROOF BURGUNDY",
        "qty": 12.0,
        "unit_price": 109.25,
        "value": 1311.0
      },
      {
        "prodname": "24X1KG PUTTY",
        "qty": 1.0,
        "unit_price": 267.03,
        "value": 267.03
      },
      {
        "prodname": "12X2KG PUTTY",
        "qty": 2.0,
        "unit_price": 251.07,
        "value": 502.14
      },
      {
        "prodname": "20KG PUTTY",
        "qty": 3.0,
        "unit_price": 168.98,
        "value": 506.94
      },
      {
        "prodname": "10KG PUTTY",
        "qty": 10.0,
        "unit_price": 90.05,
        "value": 900.5
      },
      {
        "prodname": "5KG PUTTY",
        "qty": 5.0,
        "unit_price": 54.29,
        "value": 271.45
      },
      {
        "prodname": "6x2KG DISTEMPER GREEN",
        "qty": 3.0,
        "unit_price": 163.67,
        "value": 491.01
      },
      {
        "prodname": "DOZEN 750ML LACQUER THINNERS",
        "qty": 2.0,
        "unit_price": 304.75,
        "value": 609.5
      },
      {
        "prodname": "200mm x 10m Membrane",
        "qty": 24.0,
        "unit_price": 0.0,
        "value": 0.0
      },
      {
        "prodname": "200mm x 10m Membrane",
        "qty": 30.0,
        "unit_price": 35.0,
        "value": 1050.0
      }
    ],
    "total": 10368.07,
    "count": 14
  },
  "competitor_forms_outstanding": 0
}