{
  "rep": "AP",
  "rep_name": "Amit Patel",
  "generated_at": "2026-06-15",
  "store": {
    "dlref": "KC054",
    "curef": "KC054",
    "customer_name": "Choice Build Matanda",
    "town": "Matanda Zone 3 Maluma Road",
    "accno": "KC054",
    "last_purchase_date": "04 Jun 2026",
    "last_purchase_amt": 990.0,
    "last_purchase_prod": "5L Q D BRONZE ENAMEL",
    "total_12m": 218562.59000000003,
    "velocity_category": "cooling",
    "health_tier": "At-Risk",
    "health_score": 46.9,
    "is_recovery": false,
    "d_current": 13136.36,
    "d30": 0.0,
    "d60": 0.0,
    "d90": 0.0,
    "d_total": 13136.36,
    "shared_account": false
  },
  "invoice": {
    "invoice_no": "131561",
    "date": "04 Jun 2026",
    "lines": [
      {
        "prodname": "20L KALAHARI CONT STONE GREY",
        "qty": 3.0,
        "unit_price": 442.75,
        "value": 1328.25
      },
      {
        "prodname": "20L KALAHARI  CONTR NIGHT SKY",
        "qty": 2.0,
        "unit_price": 442.75,
        "value": 885.5
      },
      {
        "prodname": "20LT KALAHARI CONT CRISP MINT",
        "qty": 4.0,
        "unit_price": 442.75,
        "value": 1771.0
      },
      {
        "prodname": "1L HIGH GLOSS (MQ) BLACK",
        "qty": 4.0,
        "unit_price": 83.95,
        "value": 335.8
      },
      {
        "prodname": "1L HIGH GLOSS (MQ) GREY",
        "qty": 4.0,
        "unit_price": 83.95,
        "value": 335.8
      },
      {
        "prodname": "5L HIGH GLOSS (MQ) GREY",
        "qty": 2.0,
        "unit_price": 289.43,
        "value": 578.86
      },
      {
        "prodname": "20L UNIVERSAL ROOF GREY",
        "qty": 3.0,
        "unit_price": 598.0,
        "value": 1794.0
      },
      {
        "prodname": "500ML COPAL VARNISH",
        "qty": 3.0,
        "unit_price": 54.38999999999999,
        "value": 163.17
      },
      {
        "prodname": "500ML LIGHT OAK VARNISH",
        "qty": 3.0,
        "unit_price": 63.38999999999999,
        "value": 190.17
      },
      {
        "prodname": "500ML DARK OAK VARNISH",
        "qty": 3.0,
        "unit_price": 63.38999999999999,
        "value": 190.17
      },
      {
        "prodname": "500ML MAHOGONY VARNISH",
        "qty": 3.0,
        "unit_price": 63.38999999999999,
        "value": 190.17
      },
      {
        "prodname": "500ML TEAK VARNISH",
        "qty": 3.0,
        "unit_price": 63.38999999999999,
        "value": 190.17
      },
      {
        "prodname": "1L COPAL VARNISH",
        "qty": 3.0,
        "unit_price": 94.3,
        "value": 282.9
      },
      {
        "prodname": "1L MAHOGONY VARNISH",
        "qty": 3.0,
        "unit_price": 109.25,
        "value": 327.75
      },
      {
        "prodname": "1L WALNUT VARNISH",
        "qty": 6.0,
        "unit_price": 109.25,
        "value": 655.5
      },
      {
        "prodname": "DOZEN 750ML LACQUER THINNERS",
        "qty": 2.0,
        "unit_price": 322.0,
        "value": 644.0
      },
      {
        "prodname": "1L Q D BRONZE ENAMEL",
        "qty": 6.0,
        "unit_price": 95.0,
        "value": 570.0
      },
      {
        "prodname": "5L Q D BRONZE ENAMEL",
        "qty": 3.0,
        "unit_price": 330.0,
        "value": 990.0
      }
    ],
    "total": 11423.21,
    "count": 18
  },
  "competitor_forms_outstanding": 0
}