{
  "rep": "NP",
  "rep_name": "Nikhil Panchal",
  "generated_at": "2026-07-09",
  "accounts": [
    {
      "dlref": "KM068",
      "accno": "KM068",
      "store_name": "Warden Mica",
      "score": 1.1,
      "tier": "Dead / Dormant",
      "days_since_purchase": 560
    },
    {
      "dlref": "KH017",
      "accno": "KH017",
      "store_name": "Capstan Trading 896 CC",
      "score": 1.1,
      "tier": "Dead / Dormant",
      "days_since_purchase": 792
    },
    {
      "dlref": "KM008",
      "accno": "KM008",
      "store_name": "Maxi Save Hardware Corporation",
      "score": 2.2,
      "tier": "Dead / Dormant",
      "days_since_purchase": 436
    },
    {
      "dlref": "KB047",
      "accno": "KB047",
      "store_name": "Sunshine 786 Trading",
      "score": 2.2,
      "tier": "Dead / Dormant",
      "days_since_purchase": 513
    },
    {
      "dlref": "KS111",
      "accno": "KS111",
      "store_name": "Speedy Hardware",
      "score": 3.3,
      "tier": "Dead / Dormant",
      "days_since_purchase": 706
    },
    {
      "dlref": "KQ012",
      "accno": "KQ012",
      "store_name": "Sembro Hardware T A Concrete &",
      "score": 4.3,
      "tier": "Dead / Dormant",
      "days_since_purchase": 758
    },
    {
      "dlref": "KS128",
      "accno": "KS128",
      "store_name": "Steel City Hardware",
      "score": 4.3,
      "tier": "Dead / Dormant",
      "days_since_purchase": 392
    },
    {
      "dlref": "KL037",
      "accno": "KL037",
      "store_name": "Lavender Moon Trading ta",
      "score": 4.5,
      "tier": "Dead / Dormant",
      "days_since_purchase": 217
    },
    {
      "dlref": "KQ005",
      "accno": "KQ005",
      "store_name": "Qwa Qwa HW - TA Mica HWare",
      "score": 5.5,
      "tier": "Dead / Dormant",
      "days_since_purchase": 450
    },
    {
      "dlref": "KF016",
      "accno": "KF016",
      "store_name": "Friends",
      "score": 6.5,
      "tier": "Dead / Dormant",
      "days_since_purchase": 561
    },
    {
      "dlref": "KA078",
      "accno": "KA078",
      "store_name": "Asif Cash & Carry & Hardware",
      "score": 6.6,
      "tier": "Dead / Dormant",
      "days_since_purchase": 303
    },
    {
      "dlref": "KN004",
      "accno": "KN004",
      "store_name": "Neha HW & Bldg. Mat.",
      "score": 7.6,
      "tier": "Dead / Dormant",
      "days_since_purchase": 441
    },
    {
      "dlref": "KM056",
      "accno": "KM056",
      "store_name": "Madina PropertY Trust",
      "score": 7.6,
      "tier": "Dead / Dormant",
      "days_since_purchase": 717
    },
    {
      "dlref": "KM143",
      "accno": "KM143",
      "store_name": "Wellmark Investments",
      "score": 7.6,
      "tier": "Dead / Dormant",
      "days_since_purchase": 514
    },
    {
      "dlref": "KA040",
      "accno": "KA040",
      "store_name": "A & S Enterprises (Pty) Ltd",
      "score": 8.4,
      "tier": "Dead / Dormant",
      "days_since_purchase": 679
    },
    {
      "dlref": "KH032",
      "accno": "KH032",
      "store_name": "Hardware Hub",
      "score": 9.5,
      "tier": "Dead / Dormant",
      "days_since_purchase": 576
    },
    {
      "dlref": "KM148",
      "accno": "KM148",
      "store_name": "Aaliya Hardware",
      "score": 10.9,
      "tier": "Dead / Dormant",
      "days_since_purchase": 421
    },
    {
      "dlref": "KM011",
      "accno": "KM011",
      "store_name": "Quick Save Hardware",
      "score": 10.9,
      "tier": "Dead / Dormant",
      "days_since_purchase": 582
    },
    {
      "dlref": "KB093",
      "accno": "KB093",
      "store_name": "Baskid Nondabuya General Trd",
      "score": 11.7,
      "tier": "Dead / Dormant",
      "days_since_purchase": 434
    },
    {
      "dlref": "KZ008/1",
      "accno": "KZ008_1",
      "store_name": "Zonelite Enterprises Pty Ltd",
      "score": 15.3,
      "tier": "Dead / Dormant",
      "days_since_purchase": 317
    },
    {
      "dlref": "KA045",
      "accno": "KA045",
      "store_name": "Africa Hardware",
      "score": 18.7,
      "tier": "Dead / Dormant",
      "days_since_purchase": 300
    },
    {
      "dlref": "KS003",
      "accno": "KS003",
      "store_name": "S.M. Hardware",
      "score": 19.0,
      "tier": "Dead / Dormant",
      "days_since_purchase": 243
    },
    {
      "dlref": "KK036",
      "accno": "KK036",
      "store_name": "Khotawala Hardware",
      "score": 22.7,
      "tier": "At-Risk",
      "days_since_purchase": 29
    },
    {
      "dlref": "KF022",
      "accno": "KF022",
      "store_name": "F A P Holdings Pty Ltd ta KGN",
      "score": 23.2,
      "tier": "Dead / Dormant",
      "days_since_purchase": 129
    },
    {
      "dlref": "KL006",
      "accno": "KL006",
      "store_name": "LCS Wholesalers (Kanye) P L",
      "score": 23.2,
      "tier": "Dead / Dormant",
      "days_since_purchase": 203
    },
    {
      "dlref": "KN024/3",
      "accno": "KN024_3",
      "store_name": "Navisha Investments Pty Ltd",
      "score": 23.2,
      "tier": "Dead / Dormant",
      "days_since_purchase": 227
    },
    {
      "dlref": "KA110",
      "accno": "KA110",
      "store_name": "Ace Steel And Roofing",
      "score": 23.2,
      "tier": "At-Risk",
      "days_since_purchase": 30
    },
    {
      "dlref": "KJ039",
      "accno": "KJ039",
      "store_name": "Jabula HW",
      "score": 25.9,
      "tier": "Dead / Dormant",
      "days_since_purchase": 118
    },
    {
      "dlref": "KN024/7",
      "accno": "KN024_7",
      "store_name": "Navisha Investments Pty Ltd",
      "score": 27.0,
      "tier": "Dead / Dormant",
      "days_since_purchase": 227
    },
    {
      "dlref": "KS121",
      "accno": "KS121",
      "store_name": "Smart Builders",
      "score": 27.2,
      "tier": "Dead / Dormant",
      "days_since_purchase": 224
    },
    {
      "dlref": "KY004",
      "accno": "KY004",
      "store_name": "Builders Mart",
      "score": 27.5,
      "tier": "At-Risk",
      "days_since_purchase": 42
    },
    {
      "dlref": "KF032",
      "accno": "KF032",
      "store_name": "Alex Hardware",
      "score": 29.1,
      "tier": "Dead / Dormant",
      "days_since_purchase": 282
    },
    {
      "dlref": "KO009",
      "accno": "KO009",
      "store_name": "One Price Store",
      "score": 30.1,
      "tier": "At-Risk",
      "days_since_purchase": 45
    },
    {
      "dlref": "KS018",
      "accno": "KS018",
      "store_name": "Shikundu Trading Store",
      "score": 31.4,
      "tier": "Dead / Dormant",
      "days_since_purchase": 122
    }
  ],
  "competitor_forms_outstanding": 0
}