{
  "rep": "AC",
  "rep_name": "Aboo Cassim",
  "date_label": "Thu 09 Jul 2026",
  "cycle_label": "AC1 \u00b7 Day 4/4",
  "mtd_sales": 378744.42000000004,
  "mtd_target": 1880636.6149999998,
  "rank": 2,
  "plan_adherence_mtd": 1.0,
  "yesterday_sales": 4160.32,
  "yesterday_leads": 0,
  "yesterday_visited_stores": [
    "Builders Den",
    "Central Build It",
    "Desai Hardware",
    "Hardware City",
    "MTS Hardware",
    "Masons Hardware (\u00d72)",
    "Paint Mart (Factory)",
    "Super Stores"
  ],
  "yesterday_visits_total": 9
}