{
  "rep": "AC",
  "rep_name": "Aboo Cassim",
  "generated_at": "2026-06-09",
  "store": {
    "dlref": "KA109",
    "curef": "KA109",
    "customer_name": "Arham @ Melrose Hardware",
    "town": "Birnam",
    "accno": "KA109",
    "last_purchase_date": "04 Jun 2026",
    "last_purchase_amt": 258.0,
    "last_purchase_prod": "DOZEN 750ML TURPENTINE",
    "total_12m": 15816.01,
    "velocity_category": null,
    "health_tier": "At-Risk",
    "health_score": 51.8,
    "is_recovery": false,
    "d_current": -146.56,
    "d30": 0.0,
    "d60": 0.0,
    "d90": 0.0,
    "d_total": -146.56,
    "shared_account": false
  },
  "invoice": {
    "invoice_no": "131553",
    "date": "04 Jun 2026",
    "lines": [
      {
        "prodname": "20L KALAHARI  CONTR WHITE PVA",
        "qty": 3.0,
        "unit_price": 428.95,
        "value": 1286.85
      },
      {
        "prodname": "5L KALAHARI CONTR WHITE PVA",
        "qty": 5.0,
        "unit_price": 126.15,
        "value": 630.75
      },
      {
        "prodname": "1L HIGH GLOSS (MQ) BLACK",
        "qty": 9.0,
        "unit_price": 90.0,
        "value": 810.0
      },
      {
        "prodname": "1L HIGH GLOSS (MQ) GREY",
        "qty": 5.0,
        "unit_price": 90.0,
        "value": 450.0
      },
      {
        "prodname": "1L HIGH GLOSS (MQ) B YELLOW",
        "qty": 5.0,
        "unit_price": 90.0,
        "value": 450.0
      },
      {
        "prodname": "1L PLASTER & TILE BONDING LIQU",
        "qty": 12.0,
        "unit_price": 46.25,
        "value": 555.0
      },
      {
        "prodname": "5L PLASTER & TILE BONDING LIQU",
        "qty": 5.0,
        "unit_price": 150.15,
        "value": 750.75
      },
      {
        "prodname": "12X2KG CRACK FILLER",
        "qty": 1.0,
        "unit_price": 580.0,
        "value": 580.0
      },
      {
        "prodname": "24x500GM CRACK FILLER",
        "qty": 1.0,
        "unit_price": 430.0,
        "value": 430.0
      },
      {
        "prodname": "Doz x 50ML STAINERS BLACK",
        "qty": 1.0,
        "unit_price": 180.0,
        "value": 180.0
      },
      {
        "prodname": "Doz x 50ML STAINERS BLUE",
        "qty": 1.0,
        "unit_price": 180.0,
        "value": 180.0
      },
      {
        "prodname": "Doz x 50ML STAINERS RED",
        "qty": 1.0,
        "unit_price": 180.0,
        "value": 180.0
      },
      {
        "prodname": "DOZEN 750ML LACQUER THINNERS",
        "qty": 1.0,
        "unit_price": 315.0,
        "value": 315.0
      },
      {
        "prodname": "DOZEN 750ML TURPENTINE",
        "qty": 1.0,
        "unit_price": 258.0,
        "value": 258.0
      }
    ],
    "total": 7056.35,
    "count": 14
  },
  "competitor_forms_outstanding": 0
}